setup.py
test_distmlcourse/Binomialdistribution.py
test_distmlcourse/Gaussiandistribution.py
test_distmlcourse/Generaldistribution.py
test_distmlcourse/__init__.py
test_distmlcourse.egg-info/PKG-INFO
test_distmlcourse.egg-info/SOURCES.txt
test_distmlcourse.egg-info/dependency_links.txt
test_distmlcourse.egg-info/not-zip-safe
test_distmlcourse.egg-info/top_level.txt